slicerator/__init__.py
slicerator/_version.py
slicerator-1.0.0.dist-info/METADATA
slicerator-1.0.0.dist-info/RECORD
slicerator-1.0.0.dist-info/WHEEL
slicerator-1.0.0.dist-info/top_level.txt
