Metadata-Version: 1.1
Name: slicerator
Version: 1.0.0
Summary: A lazy-loading, fancy-sliceable iterable.
Home-page: http://github.com/soft-matter/slicerator
Author: Daniel B. Allan
Author-email: daniel.b.allan@gmail.com
License: BSD
Platform: Cross platform (Linux
Platform: Mac OSX
Platform: Windows)
Classifier: Development Status :: 4 - Beta
Classifier: Programming Language :: Python :: 2
Classifier: Programming Language :: Python :: 2.6
Classifier: Programming Language :: Python :: 2.7
Classifier: Programming Language :: Python :: 3
Classifier: Programming Language :: Python :: 3.3
Classifier: Programming Language :: Python :: 3.4
Classifier: Programming Language :: Python :: 3.5
